lineagentic_catalog/__init__.py
lineagentic_catalog/api_generator/__init__.py
lineagentic_catalog/api_generator/generator.py
lineagentic_catalog/api_generator/run_generator.py
lineagentic_catalog/cli_generator/__init__.py
lineagentic_catalog/cli_generator/generator.py
lineagentic_catalog/cli_generator/generator_backup.py
lineagentic_catalog/cli_generator/run_generator.py
lineagentic_catalog/config/__init__.py
lineagentic_catalog/config/aspects.yaml
lineagentic_catalog/config/core.yaml
lineagentic_catalog/config/entities.yaml
lineagentic_catalog/config/main_registry.yaml
lineagentic_catalog/config/relationships.yaml
lineagentic_catalog/config/urn_patterns.yaml
lineagentic_catalog/config/utilities.yaml
lineagentic_catalog/registry/__init__.py
lineagentic_catalog/registry/factory.py
lineagentic_catalog/registry/generators.py
lineagentic_catalog/registry/loaders.py
lineagentic_catalog/registry/validators.py
lineagentic_catalog/registry/writers.py
lineagentic_catalog/scripts/__init__.py
lineagentic_catalog/scripts/generate_api.py
lineagentic_catalog/scripts/generate_cli.py
lineagentic_catalog/scripts/logging_example.py
lineagentic_catalog/utils/__init__.py
lineagentic_catalog/utils/logging_config.py
lineagentic_catalog-0.7.0.dist-info/licenses/LICENSE
lineagentic_catalog-0.7.0.dist-info/METADATA
lineagentic_catalog-0.7.0.dist-info/WHEEL
lineagentic_catalog-0.7.0.dist-info/entry_points.txt
lineagentic_catalog-0.7.0.dist-info/top_level.txt
lineagentic_catalog-0.7.0.dist-info/RECORD
