Metadata-Version: 2.4
Name: lineagentic-catalog
Version: 0.7.0
Summary: Graph-native metadata platform that turns simple YAML definitions into a fully operational, customizable, and governed data model.
Author-email: LineAgentic Team <team@lineagentic.com>
Maintainer-email: LineAgentic Team <team@lineagentic.com>
License-Expression: Apache-2.0
Project-URL: Homepage, https://lineagentic.com
Project-URL: Repository, https://github.com/lineagentic/lineagentic-catalog
Project-URL: Documentation, https://github.com/lineagentic/lineagentic-catalog#readme
Project-URL: Issues, https://github.com/lineagentic/lineagentic-catalog/issues
Keywords: neo4j,metadata,registry,lineage,catalog
Classifier: Development Status :: 3 - Alpha
Classifier: Intended Audience :: Developers
Classifier: Operating System :: OS Independent
Classifier: Programming Language :: Python :: 3
Classifier: Programming Language :: Python :: 3.8
Classifier: Programming Language :: Python :: 3.9
Classifier: Programming Language :: Python :: 3.10
Classifier: Programming Language :: Python :: 3.11
Classifier: Programming Language :: Python :: 3.12
Requires-Python: >=3.8
License-File: LICENSE
Requires-Dist: fastapi>=0.68.0
Requires-Dist: pydantic>=1.8.0
Requires-Dist: neo4j>=4.4.0
Requires-Dist: pyyaml>=5.4.0
Requires-Dist: uvicorn>=0.15.0
Requires-Dist: python-multipart>=0.0.5
Requires-Dist: click>=8.0.0
Provides-Extra: dev
Requires-Dist: pytest>=6.0.0; extra == "dev"
Requires-Dist: pytest-asyncio>=0.15.0; extra == "dev"
Requires-Dist: black>=21.0.0; extra == "dev"
Requires-Dist: flake8>=3.8.0; extra == "dev"
Requires-Dist: mypy>=0.910; extra == "dev"
Requires-Dist: twine>=3.0.0; extra == "dev"
Requires-Dist: build>=0.10.0; extra == "dev"
Dynamic: license-file
